{  
    "E":{  
        "v":"0",
        "b":"Hypocrisy",
        "T":"Hypocrisy-tbvf",
        "K":".html",
        "X":"q107",
        "O":"OEBPS/Hypocrisy-tbvf.content.json",
        "A":[  
            {  
                "T":"xml:lang",
                "d":"en"
            },
            {  
                "T":"xmlns",
                "d":"http://www.w3.org/1999/xhtml"
            },
            {  
                "T":"xmlns:html",
                "d":"http://www.w3.org/1999/xhtml"
            },
            {  
                "T":"xmlns:epub",
                "d":"http://www.idpf.org/2007/ops"
            }
        ],
        "I":[  
            {  
                "H":"stylesheet.css"
            }
        ],
        "L":[  
            {  
                "B":"bookbody",
                "C":"/4",
                "D":[  
                    {  
                        "B":"div",
                        "C":"/4/2",
                        "A":[  
                            {  
                                "T":"class",
                                "d":"main-document-section"
                            }
                        ],
                        "D":[  
                            {  
                                "B":"div",
                                "C":"/4/2/2[Hypocrisy_TBVF_EveryMansBible]",
                                "A":[  
                                    {  
                                        "T":"id",
                                        "d":"Hypocrisy_TBVF_EveryMansBible"
                                    }
                                ],
                                "D":[  
                                    {  
                                        "B":"#text",
                                        "C":"/4/2/2[Hypocrisy_TBVF_EveryMansBible]/1",
                                        "J":"\n"
                                    },
                                    {  
                                        "B":"p",
                                        "C":"/4/2/2[Hypocrisy_TBVF_EveryMansBible]/2",
                                        "A":[  
                                            {  
                                                "T":"class",
                                                "d":"tbvf-h2"
                                            }
                                        ],
                                        "J":"Hy\u00ADpoc\u00ADri\u00ADsy"
                                    },
                                    {  
                                        "B":"#text",
                                        "C":"/4/2/2[Hypocrisy_TBVF_EveryMansBible]/3",
                                        "J":"\n"
                                    },
                                    {  
                                        "B":"p",
                                        "C":"/4/2/2[Hypocrisy_TBVF_EveryMansBible]/4",
                                        "A":[  
                                            {  
                                                "T":"class",
                                                "d":"tbvf-list"
                                            }
                                        ],
                                        "J":"Do not as\u00ADso\u00ADci\u00ADate with hyp\u00ADo\u00ADcrites (<a href=\"..%2Fnook%2FisaSample.xhtml#psal_26_4\">Psalm 26:4</a>)<span class=\"print ital\"> .\u00A0.\u00A0. page 000</span>"
                                    },
                                    {  
                                        "B":"#text",
                                        "C":"/4/2/2[Hypocrisy_TBVF_EveryMansBible]/5",
                                        "J":"\n"
                                    },
                                    {  
                                        "B":"p",
                                        "C":"/4/2/2[Hypocrisy_TBVF_EveryMansBible]/6",
                                        "A":[  
                                            {  
                                                "T":"class",
                                                "d":"tbvf-list"
                                            }
                                        ],
                                        "J":"God hates hy\u00ADpoc\u00ADri\u00ADsy in wor\u00ADship (<a href=\"..%2Fnook%2FisaSample.xhtml#isai_29_13\">Isa\u00ADiah 29:13</a>)<span class=\"print ital\"> .\u00A0.\u00A0. page 000</span>"
                                    },
                                    {  
                                        "B":"#text",
                                        "C":"/4/2/2[Hypocrisy_TBVF_EveryMansBible]/7",
                                        "J":"\n"
                                    },
                                    {  
                                        "B":"p",
                                        "C":"/4/2/2[Hypocrisy_TBVF_EveryMansBible]/8",
                                        "A":[  
                                            {  
                                                "T":"class",
                                                "d":"tbvf-list"
                                            }
                                        ],
                                        "J":"Hyp\u00ADo\u00ADcrites pre\u00ADtend to be de\u00ADvot\u00ADed to God (<a href=\"..%2Fnook%2FisaSample.xhtml#ezek_33_31\">Eze\u00ADki\u00ADel 33:31-32</a>)<span class=\"print ital\"> .\u00A0.\u00A0. page 000</span>"
                                    },
                                    {  
                                        "B":"#text",
                                        "C":"/4/2/2[Hypocrisy_TBVF_EveryMansBible]/9",
                                        "J":"\n"
                                    },
                                    {  
                                        "B":"p",
                                        "C":"/4/2/2[Hypocrisy_TBVF_EveryMansBible]/10",
                                        "A":[  
                                            {  
                                                "T":"class",
                                                "d":"tbvf-list"
                                            }
                                        ],
                                        "J":"God finds hyp\u00ADo\u00ADcrites re\u00ADpul\u00ADsive (<a href=\"..%2Fnook%2FisaSample.xhtml#matt_23_27\">Mat\u00ADthew 23:27-28</a>)<span class=\"print ital\"> .\u00A0.\u00A0. page 000</span>"
                                    },
                                    {  
                                        "B":"#text",
                                        "C":"/4/2/2[Hypocrisy_TBVF_EveryMansBible]/11",
                                        "J":"\n"
                                    },
                                    {  
                                        "B":"p",
                                        "C":"/4/2/2[Hypocrisy_TBVF_EveryMansBible]/12",
                                        "A":[  
                                            {  
                                                "T":"class",
                                                "d":"tbvf-list"
                                            }
                                        ],
                                        "J":"Be\u00ADware of hy\u00ADpoc\u00ADri\u00ADsy in your life (<a href=\"..%2Fnook%2FisaSample.xhtml#luke_12_1\">Luke 12:1-2</a>)<span class=\"print ital\"> .\u00A0.\u00A0. page 000</span>"
                                    },
                                    {  
                                        "B":"#text",
                                        "C":"/4/2/2[Hypocrisy_TBVF_EveryMansBible]/13",
                                        "J":"\n"
                                    },
                                    {  
                                        "B":"p",
                                        "C":"/4/2/2[Hypocrisy_TBVF_EveryMansBible]/14",
                                        "A":[  
                                            {  
                                                "T":"class",
                                                "d":"tbvf-list"
                                            }
                                        ],
                                        "J":"God will pun\u00ADish hy\u00ADpoc\u00ADri\u00ADsy (<a href=\"..%2Fnook%2FisaSample.xhtml#luke_20_46\">Luke 20:46-47</a>)<span class=\"print ital\"> .\u00A0.\u00A0. page 000</span>"
                                    },
                                    {  
                                        "B":"#text",
                                        "C":"/4/2/2[Hypocrisy_TBVF_EveryMansBible]/15",
                                        "J":"\n"
                                    },
                                    {  
                                        "B":"p",
                                        "C":"/4/2/2[Hypocrisy_TBVF_EveryMansBible]/16",
                                        "A":[  
                                            {  
                                                "T":"class",
                                                "d":"tbvf-list"
                                            }
                                        ],
                                        "J":"Hyp\u00ADo\u00ADcrites are worth\u00ADless (<a href=\"..%2Fnook%2FisaSample.xhtml#titu_1_16\">Ti\u00ADtus 1:16</a>)<span class=\"print ital\"> .\u00A0.\u00A0. page 000</span>"
                                    },
                                    {  
                                        "B":"#text",
                                        "C":"/4/2/2[Hypocrisy_TBVF_EveryMansBible]/17",
                                        "J":"\n"
                                    },
                                    {  
                                        "B":"p",
                                        "C":"/4/2/2[Hypocrisy_TBVF_EveryMansBible]/18",
                                        "A":[  
                                            {  
                                                "T":"class",
                                                "d":"tbvf-list"
                                            }
                                        ],
                                        "J":"Get rid of hy\u00ADpoc\u00ADri\u00ADsy (<a href=\"..%2Fnook%2FisaSample.xhtml#pet1_2_1\">1\u00A0Pe\u00ADter 2:1</a>)<span class=\"print ital\"> .\u00A0.\u00A0. page 000</span>"
                                    },
                                    {  
                                        "B":"#text",
                                        "C":"/4/2/2[Hypocrisy_TBVF_EveryMansBible]/19",
                                        "J":"\n\t"
                                    }
                                ]
                            },
                            {  
                                "B":"#text",
                                "C":"/4/2/3",
                                "J":"\n"
                            }
                        ]
                    }
                ]
            }
        ],
        "script":[  

        ]
    }
}